phenoAI/__init__.py
phenoAI/cli.py
phenoAI/gui.py
phenoAI/analysis/__init__.py
phenoAI/analysis/phenology.py
phenoAI/analysis/statistics.py
phenoAI/analysis/time_series.py
phenoAI/analysis/vegetation_indices.py
phenoAI/core/__init__.py
phenoAI/core/analyzer.py
phenoAI/core/config.py
phenoAI/core/exceptions.py
phenoAI/core/logger.py
phenoAI/pipeline/__init__.py
phenoAI/pipeline/batch_processor.py
phenoAI/pipeline/workflow.py
phenoAI/preprocessing/__init__.py
phenoAI/preprocessing/atmospheric_correction.py
phenoAI/preprocessing/image_enhancement.py
phenoAI/preprocessing/quality_control.py
phenoAI/utils/__init__.py
phenoAI/utils/date_utils.py
phenoAI/utils/file_handlers.py
phenoAI/utils/math_utils.py
phenoai_package-1.2.1.post1.dist-info/licenses/LICENSE
phenoai_package-1.2.1.post1.dist-info/METADATA
phenoai_package-1.2.1.post1.dist-info/WHEEL
phenoai_package-1.2.1.post1.dist-info/entry_points.txt
phenoai_package-1.2.1.post1.dist-info/top_level.txt
phenoai_package-1.2.1.post1.dist-info/RECORD
