Metadata-Version: 2.4
Name: phenoai-package
Version: 1.2.1.post1
Summary: Automated Phenological Analysis Package for PhenoCam Data
Author-email: Akash Kumar <akash_k@ce.iitr.ac.in>, Siddhartha Khare <siddhartha.khare@ce.iitr.ac.in>, Sergio Rossi <sergio.rossi@uqac.ca>
License-Expression: MIT
Project-URL: Homepage, https://github.com/kharesiddhartha/phenoAI
Project-URL: Bug Reports, https://github.com/kharesiddhartha/phenoAI/issues
Project-URL: Source, https://github.com/kharesiddhartha/phenoAI
Project-URL: Documentation, https://github.com/kharesiddhartha/phenoAI#readme
Keywords: phenology,computer vision,image analysis,vegetation indices,remote sensing
Platform: any
Classifier: Development Status :: 4 - Beta
Classifier: Intended Audience :: Science/Research
Classifier: Topic :: Scientific/Engineering :: Image Processing
Classifier: Topic :: Scientific/Engineering :: GIS
Classifier: Programming Language :: Python :: 3
Classifier: Programming Language :: Python :: 3.8
Classifier: Programming Language :: Python :: 3.9
Classifier: Programming Language :: Python :: 3.10
Classifier: Programming Language :: Python :: 3.11
Classifier: Programming Language :: Python :: 3.12
Classifier: Programming Language :: Python :: 3.13
Requires-Python: >=3.8
License-File: LICENSE
Requires-Dist: numpy>=1.19.0
Requires-Dist: scipy>=1.7.0
Requires-Dist: opencv-python>=4.5.0
Requires-Dist: pillow>=8.0.0
Requires-Dist: matplotlib>=3.3.0
Requires-Dist: plotly>=5.0.0
Requires-Dist: pandas>=1.3.0
Requires-Dist: pyyaml>=5.4.0
Requires-Dist: scikit-learn>=1.0.0
Requires-Dist: scikit-image>=0.18.0
Requires-Dist: tqdm>=4.60.0
Requires-Dist: h5py>=3.0.0
Requires-Dist: openpyxl>=3.0.0
Provides-Extra: dev
Requires-Dist: pytest>=6.0.0; extra == "dev"
Requires-Dist: pytest-cov>=2.10.0; extra == "dev"
Requires-Dist: flake8>=3.8.0; extra == "dev"
Requires-Dist: black>=21.0.0; extra == "dev"
Provides-Extra: docs
Requires-Dist: sphinx>=4.0.0; extra == "docs"
Requires-Dist: sphinx-rtd-theme>=0.5.0; extra == "docs"
Provides-Extra: tensorflow
Requires-Dist: tensorflow>=2.8.0; extra == "tensorflow"
Provides-Extra: all
Requires-Dist: tensorflow>=2.8.0; extra == "all"
Dynamic: license-file
Dynamic: platform
